snake/__init__.py
snake/__main__.py
snake/game.py
snake/control/__init__.py
snake/control/key.py
snake/entity/__init__.py
snake/entity/body.py
snake/entity/food.py
snake/entity/snake.py
snake/environment/__init__.py
snake/environment/terminal.py
snake/environment/window.py
tests/__init__.py
tests/fake.py
tests/control/__init__.py
tests/control/test_key.py
tests/environment/__init__.py
tests/environment/test_attributes.py
tests/snake/__init__.py
tests/snake/test_attributes.py
tests/snake/test_body.py
tests/snake/test_snake.py
cli_snakegame-1.3.0.dist-info/AUTHORS.md
cli_snakegame-1.3.0.dist-info/LICENSE.md
cli_snakegame-1.3.0.dist-info/METADATA
cli_snakegame-1.3.0.dist-info/WHEEL
cli_snakegame-1.3.0.dist-info/entry_points.txt
cli_snakegame-1.3.0.dist-info/top_level.txt
cli_snakegame-1.3.0.dist-info/RECORD
