Metadata-Version: 2.1
Name: cli-snakegame
Version: 1.3.0
Summary: A simple snake game right in your command line. Just try it, it is fun :)
Home-page: https://github.com/vyahello/snakegame-cli
Author: Volodymyr Yahello
Author-email: vyahello@gmail.com
License: UNKNOWN
Platform: UNKNOWN
Classifier: Programming Language :: Python :: 3.4
Classifier: Programming Language :: Python :: 3.5
Classifier: Programming Language :: Python :: 3.6
Classifier: Programming Language :: Python :: 3.7
Classifier: Programming Language :: Python :: 3.8
Classifier: License :: OSI Approved :: GNU General Public License v3 (GPLv3)
Classifier: Operating System :: POSIX :: Linux
Classifier: Operating System :: MacOS
Requires-Python: >=3.4
License-File: LICENSE.md
License-File: AUTHORS.md
Requires-Dist: dataclasses (==0.6)
Requires-Dist: click (==7.0.0)
